README.txt
setup.cfg
setup.py
docs/LICENSE.txt
docs/agpl-3.0.txt
src/bonner_nacht/__init__.py
src/bonner_nacht.policy.egg-info/PKG-INFO
src/bonner_nacht.policy.egg-info/SOURCES.txt
src/bonner_nacht.policy.egg-info/dependency_links.txt
src/bonner_nacht.policy.egg-info/entry_points.txt
src/bonner_nacht.policy.egg-info/namespace_packages.txt
src/bonner_nacht.policy.egg-info/not-zip-safe
src/bonner_nacht.policy.egg-info/requires.txt
src/bonner_nacht.policy.egg-info/top_level.txt
src/bonner_nacht/policy/__init__.py
src/bonner_nacht/policy/configure.zcml
src/bonner_nacht/policy/profiles/default/metadata.xml
src/bonner_nacht/policy/profiles/default/properties.xml