Metadata-Version: 1.1
Name: bonner-nacht.policy
Version: 1.2.0
Summary: Bonner Nacht Site Policy
Home-page: https://gitorious.org/bonner-nacht
Author: Fabian Köster
Author-email: koesterreich@fastmail.fm
License: agpl
Platform: UNKNOWN
Classifier: Environment :: Web Environment
Classifier: Framework :: Plone
Classifier: Operating System :: OS Independent
Classifier: Programming Language :: Python
Classifier: Programming Language :: Python :: 2.7
Classifier: Topic :: Software Development :: Libraries :: Python Modules
